yafowil.bootstrap-1.3.2-nspkg.pth
yafowil/bootstrap/__init__.py
yafowil/bootstrap/common.py
yafowil/bootstrap/tests.py
yafowil/bootstrap/resources/css/bootstrap-theme.css
yafowil/bootstrap/resources/css/bootstrap-theme.min.css
yafowil/bootstrap/resources/css/bootstrap.css
yafowil/bootstrap/resources/css/bootstrap.min.css
yafowil/bootstrap/resources/fonts/glyphicons-halflings-regular.eot
yafowil/bootstrap/resources/fonts/glyphicons-halflings-regular.svg
yafowil/bootstrap/resources/fonts/glyphicons-halflings-regular.ttf
yafowil/bootstrap/resources/fonts/glyphicons-halflings-regular.woff
yafowil/bootstrap/resources/js/bootstrap.js
yafowil/bootstrap/resources/js/bootstrap.min.js
yafowil.bootstrap-1.3.2.dist-info/LICENSE.rst
yafowil.bootstrap-1.3.2.dist-info/METADATA
yafowil.bootstrap-1.3.2.dist-info/WHEEL
yafowil.bootstrap-1.3.2.dist-info/entry_points.txt
yafowil.bootstrap-1.3.2.dist-info/namespace_packages.txt
yafowil.bootstrap-1.3.2.dist-info/top_level.txt
yafowil.bootstrap-1.3.2.dist-info/RECORD
