Metadata-Version: 2.1
Name: yafowil.bootstrap
Version: 1.3.2
Summary: Bootstrap Styles for YAFOWIL
Home-page: https://github.com/conestack/yafowil.bootstrap
Author: Yafowil Contributors
Author-email: dev@conestack.org
License: Simplified BSD
Platform: UNKNOWN
Classifier: Environment :: Web Environment
Classifier: Operating System :: OS Independent
Classifier: Programming Language :: Python
Classifier: Topic :: Internet :: WWW/HTTP :: Dynamic Content
Classifier: License :: OSI Approved :: BSD License
Requires-Dist: setuptools
Requires-Dist: yafowil (>1.99)
Provides-Extra: test
Requires-Dist: yafowil[test] ; extra == 'test'
